AUTHORS.rst
LICENSE.rst
README.rst
ez_setup.py
iorient.png
iorient.xcf
setup.py
iorient/__init__.py
iorient.egg-info/PKG-INFO
iorient.egg-info/SOURCES.txt
iorient.egg-info/dependency_links.txt
iorient.egg-info/pbr.json
iorient.egg-info/requires.txt
iorient.egg-info/top_level.txt