Metadata-Version: 1.1
Name: iorient
Version: 0.1.3
Summary: Query OrientDB via IPython
Home-page: https://github.com/lebedov/iorient/
Author: Lev Givon
Author-email: lev@columbia.edu
License: BSD
Platform: UNKNOWN
Classifier: Development Status :: 3 - Alpha
Classifier: Environment :: Console
Classifier: Framework :: IPython
Classifier: Intended Audience :: Developers
Classifier: License :: OSI Approved :: BSD License
Classifier: Operating System :: OS Independent
Classifier: Programming Language :: Python
Classifier: Topic :: Software Development
Classifier: Topic :: Database
Classifier: Topic :: Database :: Front-Ends
